{
    "configurations": [
        {
            "name": "MinGW",
            "includePath": [
                "${workspaceFolder}/**",
                "D:\\projects\\my\\c\\terminal\\src",
                "D:\\projects\\my\\c\\terminal\\examples\\vcode"
            ],
            "defines": [
                "_DEBUG",
                "UNICODE",
                "_UNICODE"
            ],
            "windowsSdkVersion": "10.0.19041.0",
            "compilerPath": "C:\\Program Files (x86)\\Dev-Cpp\\MinGW64\\bin\\gcc.exe",
            "cStandard": "gnu99",
            "intelliSenseMode": "windows-gcc-x64"
        }
    ],
    "version": 4
}